apis/__init__.py
apis/build.py
apis/client.py
apis/pdu.py
apis/perf.py
apis/pr.py
config/__init__.py
config/develop.py
config/prod.py
handles/__init__.py
handles/build.py
handles/pdu.py
handles/perf.py
handles/pr.py
schemas/__init__.py
schemas/jenkins.py
schemas/pull_request.py
schemas/pull_request_job.py
schemas/test_case.py
utils/__init__.py
utils/csv_utils.py
utils/file_utils.py
utils/json_utils.py
utils/pd_utils.py
utils/xml_utils.py
birenperf_bireninfra-0.0.1.dist-info/LICENSE.txt
birenperf_bireninfra-0.0.1.dist-info/METADATA
birenperf_bireninfra-0.0.1.dist-info/WHEEL
birenperf_bireninfra-0.0.1.dist-info/top_level.txt
birenperf_bireninfra-0.0.1.dist-info/RECORD
